ingenialogger/__init__.py
ingenialogger/ingenialogger.py
ingenialogger/parser.py
ingenialogger-0.3.0.dist-info/METADATA
ingenialogger-0.3.0.dist-info/WHEEL
ingenialogger-0.3.0.dist-info/top_level.txt
ingenialogger-0.3.0.dist-info/RECORD
