Metadata-Version: 2.1
Name: ingenialogger
Version: 0.3.0
Summary: Logger library for Ingenia projects
Home-page: https://www.ingeniamc.com
Author: Ingenia Motion Control
Author-email: support@ingeniamc.com
License: UNKNOWN
Project-URL: Documentation, https://distext.ingeniamc.com/doc/ingenialogger/0.3.0
Platform: UNKNOWN
Classifier: Programming Language :: Python :: 3
Classifier: License :: OSI Approved :: MIT License
Classifier: Operating System :: OS Independent
Requires-Python: >=3.6
